{
  "schema_version": 2,
  "daily": {
    "2026-04-08": {
      "runs": 1,
      "posted": 0,
      "source_civitai_selected": 0,
      "source_rule34_selected": 0,
      "skip_no_item": 0,
      "skip_download_error": 0,
      "skip_file_too_large": 0,
      "skip_small_image": 0,
      "skip_bad_video_duration": 0,
      "skip_low_video_quality": 0,
      "skip_duplicate_hash": 0,
      "send_errors": 0,
      "runtime_sec": 0.0
    }
  },
  "lifetime": {
    "runs": 1,
    "posted": 0,
    "source_civitai_selected": 0,
    "source_rule34_selected": 0,
    "skip_no_item": 0,
    "skip_download_error": 0,
    "skip_file_too_large": 0,
    "skip_small_image": 0,
    "skip_bad_video_duration": 0,
    "skip_low_video_quality": 0,
    "skip_duplicate_hash": 0,
    "send_errors": 0,
    "runtime_sec": 0.0
  },
  "report": {}
}